{"type": "Collection", "id": "https://presentation-iiif.library.nd.edu/collection/identifier/MSNCOL8500_EAD", "label": {"en": ["William Beatty, Jr. Letters"]}, "thumbnail": [{"id": "https://image-iiif.library.nd.edu/iiif/2/identifier/MSN-COL_8500-01.a.150.jpg/full/250,/0/default.jpg", "type": "Image", "service": [{"id": "https://image-iiif.library.nd.edu/iiif/2/identifier/MSN-COL_8500-01.a.150.jpg", "type": "ImageService2", "profile": "http://iiif.io/api/image/2/level2.json"}]}], "items": [{"type": "Manifest", "id": "https://presentation-iiif.library.nd.edu/identifier/aspace_5af3821a5c7acc075fa7e4e881bae90c/manifest", "label": {"en": ["Letter. W[illiam] B[eatty, Jr.], Hanover, New Jersey, to Col. W[illia]m Beatty, Maryland"]}, "thumbnail": [{"id": "https://image-iiif.library.nd.edu/iiif/2/identifier/MSN-COL_8500-01.a.150.jpg/full/250,/0/default.jpg", "type": "Image", "service": [{"id": "https://image-iiif.library.nd.edu/iiif/2/identifier/MSN-COL_8500-01.a.150.jpg", "type": "ImageService2", "profile": "http://iiif.io/api/image/2/level2.json"}]}], "items": [{"id": "https://presentation-iiif.library.nd.edu/identifier/canvas/MSN-COL_8500-01.a.150.jpg", "type": "Canvas", "label": {"en": ["https://rarebooks library nd edu/collections/ead xml/images/MSN COL 8500/MSN COL 8500 01 a 150 jpg"]}, "height": "", "width": "", "thumbnail": [{"id": "https://image-iiif.library.nd.edu/iiif/2/identifier/MSN-COL_8500-01.a.150.jpg/full/250,/0/default.jpg", "type": "Image", "service": [{"id": "https://image-iiif.library.nd.edu/iiif/2/identifier/MSN-COL_8500-01.a.150.jpg", "type": "ImageService2", "profile": "http://iiif.io/api/image/2/level2.json"}]}], "items": [{"id": "https://presentation-iiif.library.nd.edu/identifier/annotation_page/MSN-COL_8500-01.a.150.jpg", "type": "AnnotationPage", "items": [{"id": "https://presentation-iiif.library.nd.edu/identifier/annotation/MSN-COL_8500-01.a.150.jpg", "type": "Annotation", "motivation": "painting", "target": "https://presentation-iiif.library.nd.edu/identifier/canvas/MSN-COL_8500-01.a.150.jpg", "body": {"id": "https://image-iiif.library.nd.edu/iiif/2/identifier/MSN-COL_8500-01.a.150.jpg/full/full/0/default.jpg", "type": "Image", "format": "image/jpeg", "service": [{"id": "https://image-iiif.library.nd.edu/iiif/2/identifier/MSN-COL_8500-01.a.150.jpg", "type": "ImageService2", "profile": "http://iiif.io/api/image/2/level2.json"}]}}]}]}, {"id": "https://presentation-iiif.library.nd.edu/identifier/canvas/MSN-COL_8500-01.b.150.jpg", "type": "Canvas", "label": {"en": ["https://rarebooks library nd edu/collections/ead xml/images/MSN COL 8500/MSN COL 8500 01 b 150 jpg"]}, "height": "", "width": "", "thumbnail": [{"id": "https://image-iiif.library.nd.edu/iiif/2/identifier/MSN-COL_8500-01.b.150.jpg/full/250,/0/default.jpg", "type": "Image", "service": [{"id": "https://image-iiif.library.nd.edu/iiif/2/identifier/MSN-COL_8500-01.b.150.jpg", "type": "ImageService2", "profile": "http://iiif.io/api/image/2/level2.json"}]}], "items": [{"id": "https://presentation-iiif.library.nd.edu/identifier/annotation_page/MSN-COL_8500-01.b.150.jpg", "type": "AnnotationPage", "items": [{"id": "https://presentation-iiif.library.nd.edu/identifier/annotation/MSN-COL_8500-01.b.150.jpg", "type": "Annotation", "motivation": "painting", "target": "https://presentation-iiif.library.nd.edu/identifier/canvas/MSN-COL_8500-01.b.150.jpg", "body": {"id": "https://image-iiif.library.nd.edu/iiif/2/identifier/MSN-COL_8500-01.b.150.jpg/full/full/0/default.jpg", "type": "Image", "format": "image/jpeg", "service": [{"id": "https://image-iiif.library.nd.edu/iiif/2/identifier/MSN-COL_8500-01.b.150.jpg", "type": "ImageService2", "profile": "http://iiif.io/api/image/2/level2.json"}]}}]}]}], "viewingDirection": "left-to-right", "seeAlso": [{"id": "https://presentation-iiif.library.nd.edu/identifier/aspace_5af3821a5c7acc075fa7e4e881bae90c", "type": "Dataset", "format": "application/ld+json", "profile": "https://schema.org/"}], "summary": {"en": ["Beatty informs his father of his health, and discusses his material needs. As for the military situation, \"I have no news only that we moved about a mile from our old Encampment. . . .\" In a postscript, mentions the desertion of one man and the execution for desertion of another."]}}, {"type": "Manifest", "id": "https://presentation-iiif.library.nd.edu/identifier/aspace_b8ba0bbd7092b88e4dad1837ffec713c/manifest", "label": {"en": ["Letter. W[illiam] Beatty [Jr.], Brunswick, New Jersey, to Col. William Beatty, Fred[eric]k County, Maryland"]}, "thumbnail": [{"id": "https://image-iiif.library.nd.edu/iiif/2/identifier/MSN-COL_8500-02.a.150.jpg/full/250,/0/default.jpg", "type": "Image", "service": [{"id": "https://image-iiif.library.nd.edu/iiif/2/identifier/MSN-COL_8500-02.a.150.jpg", "type": "ImageService2", "profile": "http://iiif.io/api/image/2/level2.json"}]}], "items": [{"id": "https://presentation-iiif.library.nd.edu/identifier/canvas/MSN-COL_8500-02.a.150.jpg", "type": "Canvas", "label": {"en": ["https://rarebooks library nd edu/collections/ead xml/images/MSN COL 8500/MSN COL 8500 02 a 150 jpg"]}, "height": "", "width": "", "thumbnail": [{"id": "https://image-iiif.library.nd.edu/iiif/2/identifier/MSN-COL_8500-02.a.150.jpg/full/250,/0/default.jpg", "type": "Image", "service": [{"id": "https://image-iiif.library.nd.edu/iiif/2/identifier/MSN-COL_8500-02.a.150.jpg", "type": "ImageService2", "profile": "http://iiif.io/api/image/2/level2.json"}]}], "items": [{"id": "https://presentation-iiif.library.nd.edu/identifier/annotation_page/MSN-COL_8500-02.a.150.jpg", "type": "AnnotationPage", "items": [{"id": "https://presentation-iiif.library.nd.edu/identifier/annotation/MSN-COL_8500-02.a.150.jpg", "type": "Annotation", "motivation": "painting", "target": "https://presentation-iiif.library.nd.edu/identifier/canvas/MSN-COL_8500-02.a.150.jpg", "body": {"id": "https://image-iiif.library.nd.edu/iiif/2/identifier/MSN-COL_8500-02.a.150.jpg/full/full/0/default.jpg", "type": "Image", "format": "image/jpeg", "service": [{"id": "https://image-iiif.library.nd.edu/iiif/2/identifier/MSN-COL_8500-02.a.150.jpg", "type": "ImageService2", "profile": "http://iiif.io/api/image/2/level2.json"}]}}]}]}, {"id": "https://presentation-iiif.library.nd.edu/identifier/canvas/MSN-COL_8500-02.b.150.jpg", "type": "Canvas", "label": {"en": ["https://rarebooks library nd edu/collections/ead xml/images/MSN COL 8500/MSN COL 8500 02 b 150 jpg"]}, "height": "", "width": "", "thumbnail": [{"id": "https://image-iiif.library.nd.edu/iiif/2/identifier/MSN-COL_8500-02.b.150.jpg/full/250,/0/default.jpg", "type": "Image", "service": [{"id": "https://image-iiif.library.nd.edu/iiif/2/identifier/MSN-COL_8500-02.b.150.jpg", "type": "ImageService2", "profile": "http://iiif.io/api/image/2/level2.json"}]}], "items": [{"id": "https://presentation-iiif.library.nd.edu/identifier/annotation_page/MSN-COL_8500-02.b.150.jpg", "type": "AnnotationPage", "items": [{"id": "https://presentation-iiif.library.nd.edu/identifier/annotation/MSN-COL_8500-02.b.150.jpg", "type": "Annotation", "motivation": "painting", "target": "https://presentation-iiif.library.nd.edu/identifier/canvas/MSN-COL_8500-02.b.150.jpg", "body": {"id": "https://image-iiif.library.nd.edu/iiif/2/identifier/MSN-COL_8500-02.b.150.jpg/full/full/0/default.jpg", "type": "Image", "format": "image/jpeg", "service": [{"id": "https://image-iiif.library.nd.edu/iiif/2/identifier/MSN-COL_8500-02.b.150.jpg", "type": "ImageService2", "profile": "http://iiif.io/api/image/2/level2.json"}]}}]}]}, {"id": "https://presentation-iiif.library.nd.edu/identifier/canvas/MSN-COL_8500-02.c.150.jpg", "type": "Canvas", "label": {"en": ["https://rarebooks library nd edu/collections/ead xml/images/MSN COL 8500/MSN COL 8500 02 c 150 jpg"]}, "height": "", "width": "", "thumbnail": [{"id": "https://image-iiif.library.nd.edu/iiif/2/identifier/MSN-COL_8500-02.c.150.jpg/full/250,/0/default.jpg", "type": "Image", "service": [{"id": "https://image-iiif.library.nd.edu/iiif/2/identifier/MSN-COL_8500-02.c.150.jpg", "type": "ImageService2", "profile": "http://iiif.io/api/image/2/level2.json"}]}], "items": [{"id": "https://presentation-iiif.library.nd.edu/identifier/annotation_page/MSN-COL_8500-02.c.150.jpg", "type": "AnnotationPage", "items": [{"id": "https://presentation-iiif.library.nd.edu/identifier/annotation/MSN-COL_8500-02.c.150.jpg", "type": "Annotation", "motivation": "painting", "target": "https://presentation-iiif.library.nd.edu/identifier/canvas/MSN-COL_8500-02.c.150.jpg", "body": {"id": "https://image-iiif.library.nd.edu/iiif/2/identifier/MSN-COL_8500-02.c.150.jpg/full/full/0/default.jpg", "type": "Image", "format": "image/jpeg", "service": [{"id": "https://image-iiif.library.nd.edu/iiif/2/identifier/MSN-COL_8500-02.c.150.jpg", "type": "ImageService2", "profile": "http://iiif.io/api/image/2/level2.json"}]}}]}]}], "viewingDirection": "left-to-right", "seeAlso": [{"id": "https://presentation-iiif.library.nd.edu/identifier/aspace_b8ba0bbd7092b88e4dad1837ffec713c", "type": "Dataset", "format": "application/ld+json", "profile": "https://schema.org/"}], "summary": {"en": ["Updates on Beatty's health and other matters. Beatty thanks his father for monies received and promises to \"Restrain from Extrovagancies.\" He also requests that his father pay no heed to \"Reports Raisd to injure Me\" by \"some Cowardly Rascal,\" but provides no further details. Closes with news on British activities in the New York City area."]}}, {"type": "Manifest", "id": "https://presentation-iiif.library.nd.edu/identifier/aspace_372ade732fbb91cbf45f9f626a8a7c37/manifest", "label": {"en": ["Letter. W[illiam] B[eatty, Jr.], Philadelphia, Pennsylvania, to Col. William Beatty, Maryland"]}, "thumbnail": [{"id": "https://image-iiif.library.nd.edu/iiif/2/identifier/MSN-COL_8500-03.a.150.jpg/full/250,/0/default.jpg", "type": "Image", "service": [{"id": "https://image-iiif.library.nd.edu/iiif/2/identifier/MSN-COL_8500-03.a.150.jpg", "type": "ImageService2", "profile": "http://iiif.io/api/image/2/level2.json"}]}], "items": [{"id": "https://presentation-iiif.library.nd.edu/identifier/canvas/MSN-COL_8500-03.a.150.jpg", "type": "Canvas", "label": {"en": ["https://rarebooks library nd edu/collections/ead xml/images/MSN COL 8500/MSN COL 8500 03 a 150 jpg"]}, "height": "", "width": "", "thumbnail": [{"id": "https://image-iiif.library.nd.edu/iiif/2/identifier/MSN-COL_8500-03.a.150.jpg/full/250,/0/default.jpg", "type": "Image", "service": [{"id": "https://image-iiif.library.nd.edu/iiif/2/identifier/MSN-COL_8500-03.a.150.jpg", "type": "ImageService2", "profile": "http://iiif.io/api/image/2/level2.json"}]}], "items": [{"id": "https://presentation-iiif.library.nd.edu/identifier/annotation_page/MSN-COL_8500-03.a.150.jpg", "type": "AnnotationPage", "items": [{"id": "https://presentation-iiif.library.nd.edu/identifier/annotation/MSN-COL_8500-03.a.150.jpg", "type": "Annotation", "motivation": "painting", "target": "https://presentation-iiif.library.nd.edu/identifier/canvas/MSN-COL_8500-03.a.150.jpg", "body": {"id": "https://image-iiif.library.nd.edu/iiif/2/identifier/MSN-COL_8500-03.a.150.jpg/full/full/0/default.jpg", "type": "Image", "format": "image/jpeg", "service": [{"id": "https://image-iiif.library.nd.edu/iiif/2/identifier/MSN-COL_8500-03.a.150.jpg", "type": "ImageService2", "profile": "http://iiif.io/api/image/2/level2.json"}]}}]}]}, {"id": "https://presentation-iiif.library.nd.edu/identifier/canvas/MSN-COL_8500-03.b.150.jpg", "type": "Canvas", "label": {"en": ["https://rarebooks library nd edu/collections/ead xml/images/MSN COL 8500/MSN COL 8500 03 b 150 jpg"]}, "height": "", "width": "", "thumbnail": [{"id": "https://image-iiif.library.nd.edu/iiif/2/identifier/MSN-COL_8500-03.b.150.jpg/full/250,/0/default.jpg", "type": "Image", "service": [{"id": "https://image-iiif.library.nd.edu/iiif/2/identifier/MSN-COL_8500-03.b.150.jpg", "type": "ImageService2", "profile": "http://iiif.io/api/image/2/level2.json"}]}], "items": [{"id": "https://presentation-iiif.library.nd.edu/identifier/annotation_page/MSN-COL_8500-03.b.150.jpg", "type": "AnnotationPage", "items": [{"id": "https://presentation-iiif.library.nd.edu/identifier/annotation/MSN-COL_8500-03.b.150.jpg", "type": "Annotation", "motivation": "painting", "target": "https://presentation-iiif.library.nd.edu/identifier/canvas/MSN-COL_8500-03.b.150.jpg", "body": {"id": "https://image-iiif.library.nd.edu/iiif/2/identifier/MSN-COL_8500-03.b.150.jpg/full/full/0/default.jpg", "type": "Image", "format": "image/jpeg", "service": [{"id": "https://image-iiif.library.nd.edu/iiif/2/identifier/MSN-COL_8500-03.b.150.jpg", "type": "ImageService2", "profile": "http://iiif.io/api/image/2/level2.json"}]}}]}]}], "viewingDirection": "left-to-right", "seeAlso": [{"id": "https://presentation-iiif.library.nd.edu/identifier/aspace_372ade732fbb91cbf45f9f626a8a7c37", "type": "Dataset", "format": "application/ld+json", "profile": "https://schema.org/"}], "summary": {"en": ["Beatty communicates his need for summer stockings and reports that he recently traveled to Cecil County, Maryland to retrieve baggage belonging to the officers. He also describes seeing a French frigate leading several captured British ships. Opines that he will soon come home because \"there is no Doubt of a french war which I Expect will put a stop to our troubles.\""]}}, {"type": "Manifest", "id": "https://presentation-iiif.library.nd.edu/identifier/aspace_6cf5183c85902a1cf148d71ab3657c16/manifest", "label": {"en": ["Letter. W[illiam] B[eatty, Jr.], White Plains, New York, to \"Hounoured Father\" [Col. William Beatty]"]}, "thumbnail": [{"id": "https://image-iiif.library.nd.edu/iiif/2/identifier/MSN-COL_8500-04.a.150.jpg/full/250,/0/default.jpg", "type": "Image", "service": [{"id": "https://image-iiif.library.nd.edu/iiif/2/identifier/MSN-COL_8500-04.a.150.jpg", "type": "ImageService2", "profile": "http://iiif.io/api/image/2/level2.json"}]}], "items": [{"id": "https://presentation-iiif.library.nd.edu/identifier/canvas/MSN-COL_8500-04.a.150.jpg", "type": "Canvas", "label": {"en": ["https://rarebooks library nd edu/collections/ead xml/images/MSN COL 8500/MSN COL 8500 04 a 150 jpg"]}, "height": "", "width": "", "thumbnail": [{"id": "https://image-iiif.library.nd.edu/iiif/2/identifier/MSN-COL_8500-04.a.150.jpg/full/250,/0/default.jpg", "type": "Image", "service": [{"id": "https://image-iiif.library.nd.edu/iiif/2/identifier/MSN-COL_8500-04.a.150.jpg", "type": "ImageService2", "profile": "http://iiif.io/api/image/2/level2.json"}]}], "items": [{"id": "https://presentation-iiif.library.nd.edu/identifier/annotation_page/MSN-COL_8500-04.a.150.jpg", "type": "AnnotationPage", "items": [{"id": "https://presentation-iiif.library.nd.edu/identifier/annotation/MSN-COL_8500-04.a.150.jpg", "type": "Annotation", "motivation": "painting", "target": "https://presentation-iiif.library.nd.edu/identifier/canvas/MSN-COL_8500-04.a.150.jpg", "body": {"id": "https://image-iiif.library.nd.edu/iiif/2/identifier/MSN-COL_8500-04.a.150.jpg/full/full/0/default.jpg", "type": "Image", "format": "image/jpeg", "service": [{"id": "https://image-iiif.library.nd.edu/iiif/2/identifier/MSN-COL_8500-04.a.150.jpg", "type": "ImageService2", "profile": "http://iiif.io/api/image/2/level2.json"}]}}]}]}, {"id": "https://presentation-iiif.library.nd.edu/identifier/canvas/MSN-COL_8500-04.b.150.jpg", "type": "Canvas", "label": {"en": ["https://rarebooks library nd edu/collections/ead xml/images/MSN COL 8500/MSN COL 8500 04 b 150 jpg"]}, "height": "", "width": "", "thumbnail": [{"id": "https://image-iiif.library.nd.edu/iiif/2/identifier/MSN-COL_8500-04.b.150.jpg/full/250,/0/default.jpg", "type": "Image", "service": [{"id": "https://image-iiif.library.nd.edu/iiif/2/identifier/MSN-COL_8500-04.b.150.jpg", "type": "ImageService2", "profile": "http://iiif.io/api/image/2/level2.json"}]}], "items": [{"id": "https://presentation-iiif.library.nd.edu/identifier/annotation_page/MSN-COL_8500-04.b.150.jpg", "type": "AnnotationPage", "items": [{"id": "https://presentation-iiif.library.nd.edu/identifier/annotation/MSN-COL_8500-04.b.150.jpg", "type": "Annotation", "motivation": "painting", "target": "https://presentation-iiif.library.nd.edu/identifier/canvas/MSN-COL_8500-04.b.150.jpg", "body": {"id": "https://image-iiif.library.nd.edu/iiif/2/identifier/MSN-COL_8500-04.b.150.jpg/full/full/0/default.jpg", "type": "Image", "format": "image/jpeg", "service": [{"id": "https://image-iiif.library.nd.edu/iiif/2/identifier/MSN-COL_8500-04.b.150.jpg", "type": "ImageService2", "profile": "http://iiif.io/api/image/2/level2.json"}]}}]}]}], "viewingDirection": "left-to-right", "seeAlso": [{"id": "https://presentation-iiif.library.nd.edu/identifier/aspace_6cf5183c85902a1cf148d71ab3657c16", "type": "Dataset", "format": "application/ld+json", "profile": "https://schema.org/"}], "summary": {"en": ["A letter largely dedicated to recent military events. Of particular note is Beatty's recapitulation of the joint action between the French and General Sullivan in Rhode Island. Also mentions that the British have \"Deserters of Great Numbers\" including two Hessian officers who had been American prisoners, were exchanged back to the British, but then deserted \"on Account of their Good Usage While Prisoners with the Americans.\""]}}, {"type": "Manifest", "id": "https://presentation-iiif.library.nd.edu/identifier/aspace_166c2146918d94fcecb9f9d14aa1f892/manifest", "label": {"en": ["Letter. W[illiam] Beatty [Jr.], White Plains, to Col. William Beatty, Maryland"]}, "thumbnail": [{"id": "https://image-iiif.library.nd.edu/iiif/2/identifier/MSN-COL_8500-05.a.150.jpg/full/250,/0/default.jpg", "type": "Image", "service": [{"id": "https://image-iiif.library.nd.edu/iiif/2/identifier/MSN-COL_8500-05.a.150.jpg", "type": "ImageService2", "profile": "http://iiif.io/api/image/2/level2.json"}]}], "items": [{"id": "https://presentation-iiif.library.nd.edu/identifier/canvas/MSN-COL_8500-05.a.150.jpg", "type": "Canvas", "label": {"en": ["https://rarebooks library nd edu/collections/ead xml/images/MSN COL 8500/MSN COL 8500 05 a 150 jpg"]}, "height": "", "width": "", "thumbnail": [{"id": "https://image-iiif.library.nd.edu/iiif/2/identifier/MSN-COL_8500-05.a.150.jpg/full/250,/0/default.jpg", "type": "Image", "service": [{"id": "https://image-iiif.library.nd.edu/iiif/2/identifier/MSN-COL_8500-05.a.150.jpg", "type": "ImageService2", "profile": "http://iiif.io/api/image/2/level2.json"}]}], "items": [{"id": "https://presentation-iiif.library.nd.edu/identifier/annotation_page/MSN-COL_8500-05.a.150.jpg", "type": "AnnotationPage", "items": [{"id": "https://presentation-iiif.library.nd.edu/identifier/annotation/MSN-COL_8500-05.a.150.jpg", "type": "Annotation", "motivation": "painting", "target": "https://presentation-iiif.library.nd.edu/identifier/canvas/MSN-COL_8500-05.a.150.jpg", "body": {"id": "https://image-iiif.library.nd.edu/iiif/2/identifier/MSN-COL_8500-05.a.150.jpg/full/full/0/default.jpg", "type": "Image", "format": "image/jpeg", "service": [{"id": "https://image-iiif.library.nd.edu/iiif/2/identifier/MSN-COL_8500-05.a.150.jpg", "type": "ImageService2", "profile": "http://iiif.io/api/image/2/level2.json"}]}}]}]}, {"id": "https://presentation-iiif.library.nd.edu/identifier/canvas/MSN-COL_8500-05.b.150.jpg", "type": "Canvas", "label": {"en": ["https://rarebooks library nd edu/collections/ead xml/images/MSN COL 8500/MSN COL 8500 05 b 150 jpg"]}, "height": "", "width": "", "thumbnail": [{"id": "https://image-iiif.library.nd.edu/iiif/2/identifier/MSN-COL_8500-05.b.150.jpg/full/250,/0/default.jpg", "type": "Image", "service": [{"id": "https://image-iiif.library.nd.edu/iiif/2/identifier/MSN-COL_8500-05.b.150.jpg", "type": "ImageService2", "profile": "http://iiif.io/api/image/2/level2.json"}]}], "items": [{"id": "https://presentation-iiif.library.nd.edu/identifier/annotation_page/MSN-COL_8500-05.b.150.jpg", "type": "AnnotationPage", "items": [{"id": "https://presentation-iiif.library.nd.edu/identifier/annotation/MSN-COL_8500-05.b.150.jpg", "type": "Annotation", "motivation": "painting", "target": "https://presentation-iiif.library.nd.edu/identifier/canvas/MSN-COL_8500-05.b.150.jpg", "body": {"id": "https://image-iiif.library.nd.edu/iiif/2/identifier/MSN-COL_8500-05.b.150.jpg/full/full/0/default.jpg", "type": "Image", "format": "image/jpeg", "service": [{"id": "https://image-iiif.library.nd.edu/iiif/2/identifier/MSN-COL_8500-05.b.150.jpg", "type": "ImageService2", "profile": "http://iiif.io/api/image/2/level2.json"}]}}]}]}, {"id": "https://presentation-iiif.library.nd.edu/identifier/canvas/MSN-COL_8500-05.c.150.jpg", "type": "Canvas", "label": {"en": ["https://rarebooks library nd edu/collections/ead xml/images/MSN COL 8500/MSN COL 8500 05 c 150 jpg"]}, "height": "", "width": "", "thumbnail": [{"id": "https://image-iiif.library.nd.edu/iiif/2/identifier/MSN-COL_8500-05.c.150.jpg/full/250,/0/default.jpg", "type": "Image", "service": [{"id": "https://image-iiif.library.nd.edu/iiif/2/identifier/MSN-COL_8500-05.c.150.jpg", "type": "ImageService2", "profile": "http://iiif.io/api/image/2/level2.json"}]}], "items": [{"id": "https://presentation-iiif.library.nd.edu/identifier/annotation_page/MSN-COL_8500-05.c.150.jpg", "type": "AnnotationPage", "items": [{"id": "https://presentation-iiif.library.nd.edu/identifier/annotation/MSN-COL_8500-05.c.150.jpg", "type": "Annotation", "motivation": "painting", "target": "https://presentation-iiif.library.nd.edu/identifier/canvas/MSN-COL_8500-05.c.150.jpg", "body": {"id": "https://image-iiif.library.nd.edu/iiif/2/identifier/MSN-COL_8500-05.c.150.jpg/full/full/0/default.jpg", "type": "Image", "format": "image/jpeg", "service": [{"id": "https://image-iiif.library.nd.edu/iiif/2/identifier/MSN-COL_8500-05.c.150.jpg", "type": "ImageService2", "profile": "http://iiif.io/api/image/2/level2.json"}]}}]}]}], "viewingDirection": "left-to-right", "seeAlso": [{"id": "https://presentation-iiif.library.nd.edu/identifier/aspace_166c2146918d94fcecb9f9d14aa1f892", "type": "Dataset", "format": "application/ld+json", "profile": "https://schema.org/"}], "summary": {"en": ["Beatty reports that, according to deserters, \". . . the Enemy has sent three Brigades from New York to the west Indies, the rest of their troops to fortify New york and Rhode Island for harbours for their shiping which they Intend to Destroy Our Trade with and Make no More Operations by land . . . .\" Also asks for winter clothes \"as soon as Possible for I am in great want.\""]}}], "viewingDirection": "left-to-right", "seeAlso": [{"id": "https://presentation-iiif.library.nd.edu/identifier/MSNCOL8500_EAD", "type": "Dataset", "format": "application/ld+json", "profile": "https://schema.org/"}], "provider": {"id": "https://sniteartmuseum.nd.edu/about-us/contact-us/", "type": "Agent", "label": {"en": ["Snite Museum of Art"]}, "homepage": [{"id": "https://sniteartmuseum.nd.edu", "type": "Text", "label": {"en": ["Snite Museum of Art"]}, "format": "text/html"}], "logo": [{"id": "https://sniteartmuseum.nd.edu/stylesheets/images/snite_logo@2x.png", "type": "Image", "format": "image/png", "height": 100, "width": 120}]}, "requiredStatement": {"label": {"en": ["Copyright"]}, "value": {"en": ["This field does not exist in ArchivesSpace"]}}, "rights": "Copyright status for collection materials is unknown. Transmission or reproduction of materials protected by U.S. Copyright Law (Title 17, U.S.C.) beyond that allowed by fair use requires the written permission of the copyright owners. Works not in the public domain cannot be commercially exploited without permission of the copyright owners. Responsibility for any use rests exclusively with the user.", "summary": {"en": ["The collection consists of five personal letters written by William Beatty, Jr. to his father between 17 August 1777 and 15 September 1778. Beatty strives to keep his father informed of his health, needs and movements; he also describes war-related events, some personally witnessed."]}, "metadata": [{"label": {"en": ["Creator "]}, "value": {"en": ["Beatty, William, Jr., 1758-1781"]}}, {"label": {"en": ["Campus Location"]}, "value": {"en": ["RBSC"]}}, {"label": {"en": ["Copyright"]}, "value": {"en": ["This field does not exist in ArchivesSpace"]}}, {"label": {"en": ["Conditions Governing Use"]}, "value": {"en": ["Copyright status for collection materials is unknown. Transmission or reproduction of materials protected by U.S. Copyright Law (Title 17, U.S.C.) beyond that allowed by fair use requires the written permission of the copyright owners. Works not in the public domain cannot be commercially exploited without permission of the copyright owners. Responsibility for any use rests exclusively with the user."]}}, {"label": {"en": ["Conditions Governing Access"]}, "value": {"en": ["There are no access restrictions on this collection."]}}, {"label": {"en": ["Genre/Physical Characteristic"]}, "value": {"en": ["Letters (correspondence)"]}}, {"label": {"en": ["Extent"]}, "value": {"en": ["5 folders."]}}], "@context": ["http://www.w3.org/ns/anno.jsonld", "https://presentation-iiif.library.nd.edu/extensions/partiallyDigitized", "http://iiif.io/api/presentation/3/context.json"]}